{"\u7b97\u6cd5\u8da3\u9898": [[{"url": "", "str": "\u65e5\u671f"}, {"url": "", "str": "\u9898\u76ee\u63cf\u8ff0\uff08\u70b9\u51fb\u5355\u5143\u683c\u53ef\u4ee5\u6253\u5f00\u94fe\u63a5\uff0c\u53f3\u952e\u590d\u5236\uff09"}, {"url": "", "str": "\u89e3\u7b54\u89c1\u53f3\uff08\u9632\u5267\u900f\u5206\u5272\u7ebf\uff09-------------------------------------------------------------------------------------------------------------->"}, {"url": "", "str": "\u96be\u5ea6"}, {"url": "", "str": "\u89e3\u7b54\uff08\u70b9\u51fb\u5355\u5143\u683c\u53ef\u4ee5\u6253\u5f00\u94fe\u63a5\uff0c\u53f3\u952e\u590d\u5236\uff09"}, {"url": "", "str": "\u5907\u6ce8"}], [{"url": "", "str": "2023-03-10"}, {"url": "https://codeforces.com/problemset/problem/1379/C", "str": "https://codeforces.com/problemset/problem/1379/C\n\n\u8f93\u5165 t(\u22641e4) \u8868\u793a t \u7ec4\u6570\u636e\u3002\u6240\u6709\u6570\u636e\u7684 m \u4e4b\u548c \u22641e5\u3002\n\n\u6bcf\u7ec4\u6570\u636e\u8f93\u5165 n(\u22641e9) m(\u22641e5) \u8868\u793a\u6709 m \u79cd\u7269\u54c1\uff0c\u6bcf\u79cd\u7269\u54c1\u6709\u65e0\u9650\u4e2a\uff0c\u4f60\u9700\u8981\u9009\u62e9 n \u4e2a\u3002\n\u7136\u540e\u8f93\u5165 m \u884c\uff0c\u6bcf\u884c\u4e24\u4e2a\u6570\u5b57 a[i] \u548c b[i]\uff0c\u8303\u56f4\u5728 [0,1e9]\u3002\n\n\u5982\u679c\u7b2c i \u79cd\u7269\u54c1\u9009 x \u4e2a\uff08x>0\uff09\uff0c\u6536\u76ca\u4e3a a[i]+(x-1)*b[i]\u3002\n\u8f93\u51fa\u6700\u5927\u6536\u76ca\u3002"}, {"url": "", "str": "\u8f93\u5165\n2\n4 3\n5 0\n1 4\n2 2\n\n5 3\n5 2\n4 2\n3 1\n\u8f93\u51fa\n14\n16"}, {"url": "", "str": "2000"}, {"url": "https://codeforces.com/contest/1379/submission/87405052", "str": "https://codeforces.com/contest/1379/submission/87405052\n\n\u63d0\u793a 1\uff1a\u81f3\u591a\u6709\u4e00\u4e2a\u7269\u54c1\u8981\u9009\u8d85\u8fc7 1 \u4e2a\u3002\uff08\u53cd\u8bc1\u6cd5\uff1a\u5982\u679c\u6709\u4e24\u4e2a\uff0c\u53ea\u9009 b \u66f4\u5927\u7684\u90a3\u4e2a\u66f4\u4f18\uff09\n\n\u63d0\u793a 2\uff1a\u679a\u4e3e\u7b2c i \u4e2a\u7269\u54c1\u9009\u4e86\u8d85\u8fc7 1 \u4e2a\uff0c\u90a3\u4e48\u6bd4 b[i] \u5927\u7684\u7269\u54c1\u5fc5\u987b\u9009 1 \u4e2a\u3002\n\n\u63d0\u793a 3\uff1a\u5bf9 a \u6392\u5e8f\uff0c\u7136\u540e\u4e8c\u5206\u6216\u8005\u53cc\u6307\u9488\u3002"}]], "Q": [], "\u5907\u9009\u9898\u76ee": [], "yy\u7684\u9898\u76ee": [], "TODO": [], "AC \u4e86\u4e00\u9053\u9898\u5c31\u7ed3\u675f\u4e86\u5417\uff1f": []}