{"\ud83c\udf88\u7b97\u6cd5\u8da3\u9898": [[{"url": "", "str": "\u65e5\u671f"}, {"url": "", "str": "\u9898\u89e3\u8bf7\u6ed1\u5230\u53f3\u8fb9 -->"}, {"url": "", "str": "\u6837\u4f8b"}, {"url": "", "str": "\u96be\u5ea6"}, {"url": "", "str": "\u9898\u89e3"}, {"url": "", "str": "\u5907\u6ce8"}], [{"url": "", "str": "2023-10-23"}, {"url": "https://codeforces.com/problemset/problem/1443/C", "str": "https://codeforces.com/problemset/problem/1443/C\n\n\u8f93\u5165 T(\u22642e5) \u8868\u793a T \u7ec4\u6570\u636e\u3002\u6240\u6709\u6570\u636e\u7684 n \u4e4b\u548c \u22642e5\u3002\n\u6bcf\u7ec4\u6570\u636e\u8f93\u5165 n(1\u2264n\u22642e5) \u548c\u4e24\u4e2a\u957f\u4e3a n \u7684\u6570\u7ec4 a b\uff0c\u5143\u7d20\u8303\u56f4\u5728 [1,1e9]\u3002\n\n\u628a\u4e0b\u6807 0,1,2,...,n-1 \u5206\u6210\u4e24\u7ec4\uff0c\u8bb0\u4f5c P \u548c Q\u3002\n\u5bf9\u4e8e P \u4e2d\u7684\u4e0b\u6807 i\uff0c\u8ba1\u7b97 a[i] \u7684\u6700\u5927\u503c m\u3002\n\u5bf9\u4e8e Q \u4e2d\u7684\u4e0b\u6807 j\uff0c\u8ba1\u7b97 b[j] \u7684\u548c s\u3002\n\u8f93\u51fa max(m, s) \u7684\u6700\u5c0f\u503c\u3002\n\n\u4f8b\u5982 a=[3,7,4,5], b=[2,1,2,4]\uff0c\u5982\u679c P=[0,3], Q=[1,2]\uff0c\u90a3\u4e48 m=5, s=3\uff0c\u6240\u4ee5 max(m,s)=5\u3002"}, {"url": "", "str": "\u8f93\u5165\n4\n4\n3 7 4 5\n2 1 2 4\n4\n1 2 3 4\n3 3 3 3\n2\n1 2\n10 10\n2\n10 10\n1 2\n\u8f93\u51fa\n5\n3\n2\n3"}, {"url": "", "str": "1400"}, {"url": "https://codeforces.com/contest/1443/submission/228750000", "str": "\u628a a \u548c b \u7ed1\u5728\u4e00\u8d77\uff0c\u6309\u7167 a[i] \u4ece\u5c0f\u5230\u5927\u6392\u5e8f\u3002\n\u679a\u4e3e m=a[i]\uff0c\u6240\u6709\u4e0b\u6807 <=i \u7684 b[i] \u5c31\u4e0d\u7528\u9009\u4e86\uff0c\u6240\u4ee5 s \u7b49\u4e8e b[i+1] \u4e4b\u540e\u7684\u6240\u6709\u5143\u7d20\u4e4b\u548c\u3002\n\nhttps://codeforces.com/contest/1443/submission/228750000"}]], "\ud83c\udf33\u66f4\u65b0\u65e5\u5fd7": [], "\u2753\u601d\u8003\u9898": [], "\ud83d\udcd5\u9644\u5f55": [], "AC \u4e4b\u540e": [], "TODO": [], "\u5907\u9009\u9898\u76ee": [], "QUEUE": []}