{"\ud83c\udf88\u7b97\u6cd5\u8da3\u9898": [[{"url": "", "str": "\u65e5\u671f"}, {"url": "", "str": "\u9898\u89e3\u8bf7\u6ed1\u5230\u53f3\u8fb9 -->"}, {"url": "", "str": "\u6837\u4f8b"}, {"url": "", "str": "\u96be\u5ea6"}, {"url": "", "str": "\u9898\u89e3"}, {"url": "", "str": "\u5907\u6ce8"}], [{"url": "", "str": "2023-10-09"}, {"url": "https://atcoder.jp/contests/abc321/tasks/abc321_d", "str": "https://atcoder.jp/contests/abc321/tasks/abc321_d\n\n\u8f93\u5165 n m(1\u2264n,m\u22642e5) p(1\u2264p\u22642e8)\uff0c\u548c\u957f\u5ea6\u5206\u522b\u4e3a n \u548c m \u7684\u6570\u7ec4 a \u548c b\uff0c\u5143\u7d20\u8303\u56f4 [1,1e8]\u3002\n\u8f93\u51fa\u5982\u4e0b\u7a0b\u5e8f\u6253\u5370\u7684\u503c\uff1a\nsum = 0\nfor x in a:\n    for y in b:\n        sum += min(x + y, p)\nprint(sum)"}, {"url": "", "str": "\u8f93\u5165\n2 2 7\n3 5\n6 1\n\u8f93\u51fa 24\n\n\u8f93\u5165\n1 3 2\n1\n1 1 1\n\u8f93\u51fa 6"}, {"url": "", "str": "806"}, {"url": "https://atcoder.jp/contests/abc321/submissions/46275700", "str": "\u628a a \u548c b \u4ece\u5c0f\u5230\u5927\u6392\u5e8f\u3002\n\u5012\u7740\u904d\u5386 a\uff0c\u540c\u65f6\u7ef4\u62a4\u6307\u9488 j\uff0c\u5b83\u662f\u6ee1\u8db3 a[i]+b[j] >= p \u7684\u6700\u5c0f\u503c\u3002\n\u90a3\u4e48\u5bf9\u4e8e a[i] \u6765\u8bf4\uff1a\nb[0] \u5230 b[j-1] \u4e2d\u7684\u4efb\u4f55\u6570\u548c a[i] \u76f8\u52a0\u90fd\u662f < p \u7684\uff0c\u628a a[i] * j + (b[0] + ... + b[j-1]) \u52a0\u5165\u7b54\u6848\u3002\nb[j] \u5230 b[m-1] \u4e2d\u7684\u4efb\u4f55\u6570\u548c a[i] \u76f8\u52a0\u90fd\u662f >= p \u7684\uff0c\u628a p * (m-j) \u52a0\u5165\u7b54\u6848\u3002\n\nhttps://atcoder.jp/contests/abc321/submissions/46275700"}]], "\ud83d\udcd5\u9644\u5f55": [], "\ud83c\udf33\u66f4\u65b0\u65e5\u5fd7": [], "\u2753\u601d\u8003\u9898": [], "AC \u4e4b\u540e": [], "TODO": [], "\u5907\u9009\u9898\u76ee": [], "\u5de5\u4f5c\u88681": [], "QUEUE": []}