{"\u7b97\u6cd5\u8da3\u9898": [[{"url": "", "str": "\u65e5\u671f"}, {"url": "", "str": "\u9898\u76ee\u63cf\u8ff0\uff08\u70b9\u51fb\u5355\u5143\u683c\u53ef\u4ee5\u6253\u5f00\u94fe\u63a5\uff0c\u53f3\u952e\u590d\u5236\uff09"}, {"url": "", "str": "\u89e3\u7b54\u89c1\u53f3\uff08\u9632\u5267\u900f\u5206\u5272\u7ebf\uff09-------------------------------------------------------------------------------------------------------------->"}, {"url": "", "str": "\u96be\u5ea6"}, {"url": "", "str": "\u89e3\u7b54\uff08\u70b9\u51fb\u5355\u5143\u683c\u53ef\u4ee5\u6253\u5f00\u94fe\u63a5\uff0c\u53f3\u952e\u590d\u5236\uff09"}, {"url": "", "str": "\u5907\u6ce8"}], [{"url": "", "str": "2023-01-26"}, {"url": "https://atcoder.jp/contests/arc145/tasks/arc145_a", "str": "https://atcoder.jp/contests/arc145/tasks/arc145_a\n\n\u8f93\u5165 n(2\u2264n\u22642e5) \u548c\u957f\u4e3a n \u7684\u5b57\u7b26\u4e32 s\uff0c\u4ec5\u5305\u542b 'A' \u548c 'B'\u3002\n\n\u4f60\u53ef\u4ee5\u6267\u884c\u5982\u4e0b\u64cd\u4f5c\u4efb\u610f\u591a\u6b21\uff1a\n\u9009\u62e9\u4e24\u4e2a\u76f8\u90bb\u5b57\u7b26 s[i] \u548c s[i+1]\uff0c\u628a s[i] \u66ff\u6362\u6210 'A'\uff0cs[i+1] \u66ff\u6362\u6210 'B'\u3002\n\u80fd\u5426\u4f7f s \u53d8\u6210\u56de\u6587\u4e32\uff1f\u8f93\u51fa Yes \u6216 No\u3002"}, {"url": "", "str": "\u8f93\u5165\n3\nBBA\n\u8f93\u51fa Yes\n\u89e3\u91ca \u66ff\u6362\u540e\u4e24\u4e2a\u5b57\u7b26\uff0c\u5f97\u5230 BAB\n\n\u8f93\u5165\n4\nABAB\n\u8f93\u51fa No"}, {"url": "", "str": "596"}, {"url": "https://atcoder.jp/contests/arc145/submissions/38323634", "str": "https://atcoder.jp/contests/arc145/submissions/38323634\n\n\u624b\u73a9\u3002\n\n\u64cd\u4f5c\u65b9\u6cd5\u5982\u4e0b\uff1a\n\u5982\u679c s[0]='B'\uff0c\u4ece s[1] \u5f00\u59cb\uff0c\u5de6\u5230\u53f3\u66ff\u6362\uff0c\u5f97\u5230 BAA...AAB\u3002\n\u5982\u679c s[n-1]='A'\uff0c\u4ece s[n-2] \u5f00\u59cb\uff0c\u53f3\u5230\u5de6\u66ff\u6362\uff0c\u5f97\u5230 ABB...BBA\u3002\n\n\u90a3\u4e48\uff0c\u53ea\u6709\u4e24\u79cd\u60c5\u51b5\u65e0\u6cd5\u64cd\u4f5c\uff1a\ns=\"BA\"\u3002\ns[0]='A' \u4e14 s[n-1]='B'\u3002"}]], "Q": [], "\u5907\u9009\u9898\u76ee": [], "yy\u7684\u9898\u76ee": [], "TODO": [], "AC \u4e86\u4e00\u9053\u9898\u5c31\u7ed3\u675f\u4e86\u5417\uff1f": []}